colors/__main__.py
colors/colors.py
skcolor/__main__.py
skcolor/skcolor.py
skilstak_colors-0.5.1.dist-info/METADATA
skilstak_colors-0.5.1.dist-info/WHEEL
skilstak_colors-0.5.1.dist-info/entry_points.txt
skilstak_colors-0.5.1.dist-info/top_level.txt
skilstak_colors-0.5.1.dist-info/RECORD
