Metadata-Version: 2.1
Name: skilstak-colors
Version: 0.5.1
Summary: Color library developed at Skilstak.
Home-page: https://github.com/reteps/skilstak-colors
Author: Peter Stenger
Author-email: peter.a.stenger@gmail.com
License: MIT
Platform: UNKNOWN
Classifier: License :: OSI Approved :: MIT License
Classifier: Programming Language :: Python :: 3
Classifier: Programming Language :: Python :: 3.7
